mescapi/MEScAPI.dll
mescapi/PyMEScAPI.pyd
mescapi/__init__.py
mescapi/shiboken2.abi3.dll
mescapi-0.1.13.dist-info/METADATA
mescapi-0.1.13.dist-info/WHEEL
mescapi-0.1.13.dist-info/top_level.txt
mescapi-0.1.13.dist-info/RECORD
