Metadata-Version: 2.1
Name: mescapi
Version: 0.1.13
Summary: Python API for MESc
Home-page: https://femtonics.eu
Author: Femtonics Ltd.
Author-email: support@femtonics.eu
License: UNKNOWN
Platform: nt
Classifier: Development Status :: 4 - Beta
Classifier: Topic :: Scientific/Engineering
Classifier: Intended Audience :: Science/Research
Classifier: Operating System :: Microsoft :: Windows :: Windows 10
Classifier: Programming Language :: Python :: 3
Requires-Python: >=3.6
Requires-Dist: pyside2 (==5.14.1)
